fancyviewer/__init__.py
fancyviewer/__main__.py
fancyviewer/main.py
fancyviewer/viewer.py
fancyviewer/images/black_pawn.png
fancyviewer/images/icon.png
fancyviewer/images/white_pawn.png
battlehack20_fancyviewer-1.1.1.dist-info/LICENSE
battlehack20_fancyviewer-1.1.1.dist-info/METADATA
battlehack20_fancyviewer-1.1.1.dist-info/WHEEL
battlehack20_fancyviewer-1.1.1.dist-info/top_level.txt
battlehack20_fancyviewer-1.1.1.dist-info/RECORD
